{
	"ImportPath": "github.com/phillihq/akbs",
	"GoVersion": "go1.5",
	"GodepVersion": "v60",
	"Deps": [
		{
			"ImportPath": "github.com/chasex/redis-go-cluster",
			"Comment": "v1.0.0-9-g7cf243a",
			"Rev": "7cf243aabf65070b189cf851b6d20a034fd8cacd"
		},
		{
			"ImportPath": "github.com/cihub/seelog",
			"Comment": "go1.1-81-gc510775",
			"Rev": "c510775bb50d98213cfafca75a4bc5e3fddc8d8f"
		},
		{
			"ImportPath": "github.com/garyburd/redigo/internal",
			"Rev": "4ed1111375cbeb698249ffe48dd463e9b0a63a7a"
		},
		{
			"ImportPath": "github.com/garyburd/redigo/redis",
			"Rev": "4ed1111375cbeb698249ffe48dd463e9b0a63a7a"
		},
		{
			"ImportPath": "github.com/gin-gonic/gin",
			"Comment": "v1.0rc1-219-g3d002e3",
			"Rev": "3d002e382355cafc15d706b92899b1961d5b79e9"
		},
		{
			"ImportPath": "github.com/gin-gonic/gin/binding",
			"Comment": "v1.0rc1-219-g3d002e3",
			"Rev": "3d002e382355cafc15d706b92899b1961d5b79e9"
		},
		{
			"ImportPath": "github.com/gin-gonic/gin/render",
			"Comment": "v1.0rc1-219-g3d002e3",
			"Rev": "3d002e382355cafc15d706b92899b1961d5b79e9"
		},
		{
			"ImportPath": "github.com/go-sql-driver/mysql",
			"Comment": "v1.2-112-gfb72997",
			"Rev": "fb7299726d2e68745a8805b14f2ff44b5c2cfa84"
		},
		{
			"ImportPath": "github.com/golang/protobuf/proto",
			"Rev": "8d92cf5fc15a4382f8964b08e1f42a75c0591aa3"
		},
		{
			"ImportPath": "github.com/manucorporat/sse",
			"Rev": "ee05b128a739a0fb76c7ebd3ae4810c1de808d6d"
		},
		{
			"ImportPath": "golang.org/x/net/context",
			"Rev": "d9558e5c97f85372afee28cf2b6059d7d3818919"
		},
		{
			"ImportPath": "gopkg.in/go-playground/validator.v8",
			"Comment": "v8.17.1",
			"Rev": "014792cf3e266caff1e916876be12282b33059e0"
		},
		{
			"ImportPath": "gopkg.in/gorp.v1",
			"Comment": "v1.7.1",
			"Rev": "c87af80f3cc5036b55b83d77171e156791085e2e"
		},
		{
			"ImportPath": "gopkg.in/yaml.v2",
			"Rev": "7ad95dd0798a40da1ccdff6dff35fd177b5edf40"
		}
	]
}
